num2label/__init__.py
num2label/num2label.py
num2label-1.0.0.post1.dist-info/licenses/LICENSE.txt
num2label-1.0.0.post1.dist-info/METADATA
num2label-1.0.0.post1.dist-info/WHEEL
num2label-1.0.0.post1.dist-info/top_level.txt
num2label-1.0.0.post1.dist-info/RECORD
