Metadata-Version: 2.4
Name: num2label
Version: 1.0.0.post1
Summary: A package to map numbers to text labels.
Author: Ethan Bradley
Author-email: ethan@ewbb.co.uk
License: MIT
Project-URL: Issues, https://github.com/ethanbradley/num2label/issues
Project-URL: Source, https://github.com/ethanbradley/num2label
Requires-Python: >=3.8
License-File: LICENSE.txt
Dynamic: license-file
